deep_trainer/__init__.py
deep_trainer/py.typed
deep_trainer/pytorch/__init__.py
deep_trainer/pytorch/logging.py
deep_trainer/pytorch/metric.py
deep_trainer/pytorch/trainer.py
deep_trainer-0.1.7.dist-info/licenses/LICENSE
deep_trainer-0.1.7.dist-info/METADATA
deep_trainer-0.1.7.dist-info/WHEEL
deep_trainer-0.1.7.dist-info/top_level.txt
deep_trainer-0.1.7.dist-info/RECORD
