Metadata-Version: 2.4
Name: deep-trainer
Version: 0.1.7
Summary: Helper to train deep neural networks
Home-page: https://github.com/raphaelreme/deep-trainer
Author: Raphael Reme
Author-email: raphaelreme-dev@protonmail.com
License: MIT
Keywords: deep learning,pytorch
Classifier: Development Status :: 4 - Beta
Classifier: License :: OSI Approved :: MIT License
Classifier: Natural Language :: English
Classifier: Operating System :: OS Independent
Classifier: Programming Language :: Python :: 3.9
Classifier: Programming Language :: Python :: 3.10
Classifier: Programming Language :: Python :: 3.11
Classifier: Programming Language :: Python :: 3.12
Classifier: Programming Language :: Python :: 3.13
Requires-Python: >=3.9
License-File: LICENSE
Requires-Dist: tensorboard
Requires-Dist: torch>=2.3.0
Requires-Dist: tqdm
Dynamic: license-file
